rich_elm/__init__.py
rich_elm/__main__.py
rich_elm/events.py
rich_elm/list_select.py
rich_elm/py.typed
rich_elm-0.2.0.dist-info/WHEEL
rich_elm-0.2.0.dist-info/METADATA
rich_elm-0.2.0.dist-info/RECORD
