Metadata-Version: 2.1
Name: rich-elm
Version: 0.2.0
Summary: Elm-style architecture for TUI apps, powered by Rich
Home-page: https://github.com/aatifsyed/rich-elm
License: MIT
Author: Aatif Syed
Author-email: aatifsyedyp@gmail.com
Requires-Python: >=3.8,<4.0
Classifier: License :: OSI Approved :: MIT License
Classifier: Programming Language :: Python :: 3
Classifier: Programming Language :: Python :: 3.10
Classifier: Programming Language :: Python :: 3.8
Classifier: Programming Language :: Python :: 3.9
Requires-Dist: fuzzywuzzy (>=0.18.0,<0.19.0)
Requires-Dist: lorem-text (>=2.1,<3.0)
Requires-Dist: prompt-toolkit (>=3.0.24,<4.0.0)
Requires-Dist: python-Levenshtein (>=0.12.2,<0.13.0)
Requires-Dist: returns (>=0.18.0,<0.19.0)
Requires-Dist: rich (>=11.0.0,<12.0.0)
Requires-Dist: textual (>=0.1.14,<0.2.0)
Project-URL: Repository, https://github.com/aatifsyed/rich-elm
